preAudioProcessing/__init__.py
preAudioProcessing-0.1.0.dist-info/METADATA
preAudioProcessing-0.1.0.dist-info/WHEEL
preAudioProcessing-0.1.0.dist-info/entry_points.txt
preAudioProcessing-0.1.0.dist-info/top_level.txt
preAudioProcessing-0.1.0.dist-info/RECORD
