Metadata-Version: 2.1
Name: preAudioProcessing
Version: 0.1.0
Author: Lasha Pantskhava
Author-email: lasha.pantskhava11@gmail.com
Classifier: Programming Language :: Python :: 3.9
Requires-Python: >=3.6
Requires-Dist: setuptools (~=65.5.1)
Requires-Dist: pydub (~=0.25.1)
